{"title":"Combined feed","url":"https://wduverger.github.io/feeds/all.xml","elements":[{"title":"Biofabrication of development-inspired scaffolds for regeneration of the annulus fibrosus macro- and microarchitecture (bioRxiv - amyloid)","contents":"<div class=\"highwire-article-citation highwire-citation-type-highwire-article node-biorxiv-early-2021-11-28-20211103467069\" data-pisa=\"biorxiv;2021.11.03.467069v2\" data-pisa-master=\"biorxiv;2021.11.03.467069\" data-apath=\"/biorxiv/early/2021/11/28/2021.11.03.467069.atom\" id=\"node-biorxivearly2021112820211103467069atom1825653537\"><div class=\"highwire-cite highwire-cite-highwire-article highwire-citation-biorxiv-article-pap-list clearfix\">\n\n      <span class=\"highwire-cite-title\">\n      <a href=\"/content/10.1101/2021.11.03.467069v2\" class=\"highwire-cite-linked-title\" data-icon-position=\"\" data-hide-link-title=\"0\"><span class=\"highwire-cite-title\">Biofabrication of development-inspired scaffolds for regeneration of the annulus fibrosus macro- and microarchitecture</span></a>    </span>\n  \n      <div class=\"highwire-cite-authors\"><span class=\"highwire-citation-authors\"><span class=\"highwire-citation-author first\" data-delta=\"0\"><span class=\"nlm-given-names\">Nadine</span> <span class=\"nlm-surname\">Kluser</span></span>, <span class=\"highwire-citation-author\" data-delta=\"1\"><span class=\"nlm-given-names\">Christoph</span> <span class=\"nlm-surname\">Sprecher</span></span>, <span class=\"highwire-citation-author\" data-delta=\"2\"><span class=\"nlm-given-names\">Gion Ursin</span> <span class=\"nlm-surname\">Alig</span></span>, <span class=\"highwire-citation-author\" data-delta=\"3\"><span class=\"nlm-given-names\">Sonja</span> <span class=\"nlm-surname\">Häckel</span></span>, <span class=\"highwire-citation-author\" data-delta=\"4\"><span class=\"nlm-given-names\">Christoph E.</span> <span class=\"nlm-surname\">Albers</span></span>, <span class=\"highwire-citation-author\" data-delta=\"5\"><span class=\"nlm-given-names\">Mauro</span> <span class=\"nlm-surname\">Alini</span></span>, <span class=\"highwire-citation-author\" data-delta=\"6\"><span class=\"nlm-given-names\">Sibylle</span> <span class=\"nlm-surname\">Grad</span></span>, <span class=\"highwire-citation-author\" data-delta=\"7\"><span class=\"nlm-given-names\">David</span> <span class=\"nlm-surname\">Eglin</span></span>, <span class=\"highwire-citation-author\" data-delta=\"8\"><span class=\"nlm-given-names\">Andrea</span> <span class=\"nlm-surname\">Vernengo</span></span></span></div>\n  \n      <div class=\"highwire-cite-metadata\"><span class=\"highwire-cite-metadata-journal highwire-cite-metadata\">bioRxiv </span><span class=\"highwire-cite-metadata-pages highwire-cite-metadata\">2021.11.03.467069; </span><span class=\"highwire-cite-metadata-doi highwire-cite-metadata\"><span class=\"doi_label\">doi:</span> https://doi.org/10.1101/2021.11.03.467069 </span></div>\n  \n  \n      <div class=\"highwire-cite-extras\"><div id=\"hw-make-citation-0\" class=\"hw-make-citation hw-make-citation-processed\" data-encoded-apath=\";biorxiv;early;2021;11;28;2021.11.03.467069.atom\" data-seqnum=\"0\"><a href=\"/highwire-save-citation/saveapath/%3Bbiorxiv%3Bearly%3B2021%3B11%3B28%3B2021.11.03.467069.atom/nojs/0\" id=\"link-save-citation-toggle-0\" class=\"link-save-citation-save use-ajax hw-link-save-unsave-catation link-icon ajax-processed\" title=\"Save\"><span class=\"icon-plus\"></span> <span class=\"title\">Add to Selected Citations</span></a></div></div>\n  </div>\n</div>","link":"https://www.biorxiv.org/content/10.1101/2021.11.03.467069v2","retrieved":1744479493037},{"title":"Falsehoods Programmers Believe About the IT Industry (Marko Zivanovic)","contents":"<a href=\"/falsehoods-programmers-believe-about-the-it-industry/\">Falsehoods Programmers Believe About the IT Industry</a>","link":"https://www.markozivanovic.com/falsehoods-programmers-believe-about-the-it-industry/","retrieved":1732253989252},{"title":"Setting and Managing Expectations (Marko Zivanovic)","contents":"<a href=\"/setting-and-managing-expectations/\">Setting and Managing Expectations</a>","link":"https://www.markozivanovic.com/setting-and-managing-expectations/","retrieved":1731260084427},{"title":"Effective Communication Strategies (Marko Zivanovic)","contents":"<a href=\"/effective-communication-strategies/\">Effective Communication Strategies</a>","link":"https://www.markozivanovic.com/effective-communication-strategies/","retrieved":1721237671556},{"title":"Managing High Performers (Marko Zivanovic)","contents":"<a href=\"/managing-high-performers/\">Managing High Performers</a>","link":"https://www.markozivanovic.com/managing-high-performers/","retrieved":1720805703712},{"title":"Low Latency Performance Management (LLPM) (Marko Zivanovic)","contents":"<a href=\"/low-latency-performance-management-llpm/\">Low Latency Performance Management (LLPM)</a>","link":"https://www.markozivanovic.com/low-latency-performance-management-llpm/","retrieved":1720805703714},{"title":"Developer Empowerment and Enablement Framework (DEEF) (Marko Zivanovic)","contents":"<a href=\"/developer-empowerment-and-enablement-framework-deef/\">Developer Empowerment and Enablement Framework (DEEF)</a>","link":"https://www.markozivanovic.com/developer-empowerment-and-enablement-framework-deef/","retrieved":1719336858802},{"title":"Clearly Defined Expectations and Responsibilities (CDER) (Marko Zivanovic)","contents":"<a href=\"/clearly-defined-expectations-and-responsibilities-cder/\">Clearly Defined Expectations and Responsibilities (CDER)</a>","link":"https://www.markozivanovic.com/clearly-defined-expectations-and-responsibilities-cder/","retrieved":1718732158806},{"title":"It's OK to repeat yourself on the internet (Marko Zivanovic)","contents":"<a href=\"/its-ok-to-repeat-yourself-on-the-internet/\">It's OK to repeat yourself on the internet</a>","link":"https://www.markozivanovic.com/its-ok-to-repeat-yourself-on-the-internet/","retrieved":1718645665826},{"title":"Minimally Defined Development Processes (MDDP) (Marko Zivanovic)","contents":"<a href=\"/minimally-defined-development-processes-mddp/\">Minimally Defined Development Processes (MDDP)</a>","link":"https://www.markozivanovic.com/minimally-defined-development-processes-mddp/","retrieved":1717868045090},{"title":"How AI Personalization Fuels Groupthink and Uniformity (Marko Zivanovic)","contents":"<a href=\"/how-ai-personalization-fuels-groupthink-and-uniformity/\">How AI Personalization Fuels Groupthink and Uniformity</a>","link":"https://www.markozivanovic.com/how-ai-personalization-fuels-groupthink-and-uniformity/","retrieved":1716226491112},{"title":"Towards accurate differential diagnosis with large language models (Nature - research articles)","contents":"<div class=\"c-card__layout u-full-height\">\n            \n                \n                    \n                        <div class=\"c-card__image\">\n                            <picture>\n                                <source type=\"image/webp\" srcset=\"\n                                    https://media.springernature.com/w165h90/springer-static/image/art%3A10.1038%2Fs41586-025-08869-4/MediaObjects/41586_2025_8869_Fig1_HTML.png?as=webp 160w,\n                                    https://media.springernature.com/w290h158/springer-static/image/art%3A10.1038%2Fs41586-025-08869-4/MediaObjects/41586_2025_8869_Fig1_HTML.png?as=webp 290w\" sizes=\"\n                                    (max-width: 640px) 160px,\n                                    (max-width: 1200px) 290px,\n                                    290px\">\n                                <img src=\"https://media.springernature.com/w290h158/springer-static/image/art%3A10.1038%2Fs41586-025-08869-4/MediaObjects/41586_2025_8869_Fig1_HTML.png\" alt=\"\" itemprop=\"image\">\n                            </picture>\n                        </div>\n                    \n                \n            \n            <div class=\"c-card__body u-display-flex u-flex-direction-column\">\n                <h3 class=\"c-card__title\" itemprop=\"name headline\">\n                    <a href=\"/articles/s41586-025-08869-4\" class=\"c-card__link u-link-inherit\" itemprop=\"url\" data-track=\"click\" data-track-action=\"view article\" data-track-label=\"link\">Towards accurate differential diagnosis with large language models</a>\n                </h3>\n                \n                    \n                        <div data-test=\"article-description\" class=\"c-card__summary u-mb-16 u-hide-sm-max\" itemprop=\"description\">\n                            <p>Diagnostic reasoning using an optimized large language model with a dataset comprising real-world medical cases exhibited improved differential diagnostic performance as an assistive tool for clinicians over search engines and standard medical resources.</p>\n                        </div>\n                    \n                \n                \n                    \n<ul data-test=\"author-list\" class=\"c-author-list c-author-list--compact c-author-list--truncated\">\n    <li itemprop=\"creator\" itemscope=\"\" itemtype=\"http://schema.org/Person\"><span itemprop=\"name\">Daniel McDuff</span></li><li itemprop=\"creator\" itemscope=\"\" itemtype=\"http://schema.org/Person\"><span itemprop=\"name\">Mike Schaekermann</span></li><li itemprop=\"creator\" itemscope=\"\" itemtype=\"http://schema.org/Person\"><span itemprop=\"name\">Vivek Natarajan</span></li>\n</ul>\n\n                \n                \n            </div>\n        </div>\n        \n            \n    <div class=\"c-card__section c-meta\">\n        <span class=\"c-meta__item c-meta__item--block-at-lg\" data-test=\"article.type\"><span class=\"c-meta__type\">Article</span></span><span class=\"c-meta__item c-meta__item--block-at-lg\" itemprop=\"openAccess\" data-test=\"open-access\"><span class=\"u-color-open-access\">Open Access</span></span><time class=\"c-meta__item c-meta__item--block-at-lg\" datetime=\"2025-04-09\" itemprop=\"datePublished\">09 Apr 2025</time>\n        \n        \n    </div>","link":"https://www.nature.com/articles/s41586-025-08869-4","retrieved":1744220359354},{"title":"Connectomics of predicted Sst transcriptomic types in mouse visual cortex (Nature - research articles)","contents":"<div class=\"c-card__layout u-full-height\">\n            \n                \n                    \n                        <div class=\"c-card__image\">\n                            <picture>\n                                <source type=\"image/webp\" srcset=\"\n                                    https://media.springernature.com/w165h90/springer-static/image/art%3A10.1038%2Fs41586-025-08805-6/MediaObjects/41586_2025_8805_Fig1_HTML.png?as=webp 160w,\n                                    https://media.springernature.com/w290h158/springer-static/image/art%3A10.1038%2Fs41586-025-08805-6/MediaObjects/41586_2025_8805_Fig1_HTML.png?as=webp 290w\" sizes=\"\n                                    (max-width: 640px) 160px,\n                                    (max-width: 1200px) 290px,\n                                    290px\">\n                                <img src=\"https://media.springernature.com/w290h158/springer-static/image/art%3A10.1038%2Fs41586-025-08805-6/MediaObjects/41586_2025_8805_Fig1_HTML.png\" alt=\"\" itemprop=\"image\">\n                            </picture>\n                        </div>\n                    \n                \n            \n            <div class=\"c-card__body u-display-flex u-flex-direction-column\">\n                <h3 class=\"c-card__title\" itemprop=\"name headline\">\n                    <a href=\"/articles/s41586-025-08805-6\" class=\"c-card__link u-link-inherit\" itemprop=\"url\" data-track=\"click\" data-track-action=\"view article\" data-track-label=\"link\">Connectomics of predicted <i>Sst</i> transcriptomic types in mouse visual cortex</a>\n                </h3>\n                \n                    \n                        <div data-test=\"article-description\" class=\"c-card__summary u-mb-16 u-hide-sm-max\" itemprop=\"description\">\n                            <p>The authors use Patch-seq and electron microscopy datasets to relate synaptic connectivity to the&nbsp;transcriptomic cell type of different types of inhibitory neuron.</p>\n                        </div>\n                    \n                \n                \n                    \n<ul data-test=\"author-list\" class=\"c-author-list c-author-list--compact c-author-list--truncated\">\n    <li itemprop=\"creator\" itemscope=\"\" itemtype=\"http://schema.org/Person\"><span itemprop=\"name\">Clare R. Gamlin</span></li><li itemprop=\"creator\" itemscope=\"\" itemtype=\"http://schema.org/Person\"><span itemprop=\"name\">Casey M. Schneider-Mizell</span></li><li itemprop=\"creator\" itemscope=\"\" itemtype=\"http://schema.org/Person\"><span itemprop=\"name\">Staci A. Sorensen</span></li>\n</ul>\n\n                \n                \n            </div>\n        </div>\n        \n            \n    <div class=\"c-card__section c-meta\">\n        <span class=\"c-meta__item c-meta__item--block-at-lg\" data-test=\"article.type\"><span class=\"c-meta__type\">Article</span></span><span class=\"c-meta__item c-meta__item--block-at-lg\" itemprop=\"openAccess\" data-test=\"open-access\"><span class=\"u-color-open-access\">Open Access</span></span><time class=\"c-meta__item c-meta__item--block-at-lg\" datetime=\"2025-04-09\" itemprop=\"datePublished\">09 Apr 2025</time>\n        \n        \n    </div>","link":"https://www.nature.com/articles/s41586-025-08805-6","retrieved":1744220359356},{"title":"Ultra-broadband optical amplification using nonlinear integrated waveguides (Nature - research articles)","contents":"<div class=\"c-card__layout u-full-height\">\n            \n                \n                    \n                        <div class=\"c-card__image\">\n                            <picture>\n                                <source type=\"image/webp\" srcset=\"\n                                    https://media.springernature.com/w165h90/springer-static/image/art%3A10.1038%2Fs41586-025-08824-3/MediaObjects/41586_2025_8824_Fig1_HTML.png?as=webp 160w,\n                                    https://media.springernature.com/w290h158/springer-static/image/art%3A10.1038%2Fs41586-025-08824-3/MediaObjects/41586_2025_8824_Fig1_HTML.png?as=webp 290w\" sizes=\"\n                                    (max-width: 640px) 160px,\n                                    (max-width: 1200px) 290px,\n                                    290px\">\n                                <img src=\"https://media.springernature.com/w290h158/springer-static/image/art%3A10.1038%2Fs41586-025-08824-3/MediaObjects/41586_2025_8824_Fig1_HTML.png\" alt=\"\" itemprop=\"image\">\n                            </picture>\n                        </div>\n                    \n                \n            \n            <div class=\"c-card__body u-display-flex u-flex-direction-column\">\n                <h3 class=\"c-card__title\" itemprop=\"name headline\">\n                    <a href=\"/articles/s41586-025-08824-3\" class=\"c-card__link u-link-inherit\" itemprop=\"url\" data-track=\"click\" data-track-action=\"view article\" data-track-label=\"link\">Ultra-broadband optical amplification using nonlinear integrated waveguides</a>\n                </h3>\n                \n                    \n                        <div data-test=\"article-description\" class=\"c-card__summary u-mb-16 u-hide-sm-max\" itemprop=\"description\">\n                            <p>An integrated optical parametric amplifier with an ultra-wide bandwidth was implemented using geometrically optimized low-loss nonlinear rib silicon nitride waveguides including the demonstration of broadband all-optical wavelength conversion.</p>\n                        </div>\n                    \n                \n                \n                    \n<ul data-test=\"author-list\" class=\"c-author-list c-author-list--compact c-author-list--truncated\">\n    <li itemprop=\"creator\" itemscope=\"\" itemtype=\"http://schema.org/Person\"><span itemprop=\"name\">Ping Zhao</span></li><li itemprop=\"creator\" itemscope=\"\" itemtype=\"http://schema.org/Person\"><span itemprop=\"name\">Vijay Shekhawat</span></li><li itemprop=\"creator\" itemscope=\"\" itemtype=\"http://schema.org/Person\"><span itemprop=\"name\">Peter A. Andrekson</span></li>\n</ul>\n\n                \n                \n            </div>\n        </div>\n        \n            \n    <div class=\"c-card__section c-meta\">\n        <span class=\"c-meta__item c-meta__item--block-at-lg\" data-test=\"article.type\"><span class=\"c-meta__type\">Article</span></span><span class=\"c-meta__item c-meta__item--block-at-lg\" itemprop=\"openAccess\" data-test=\"open-access\"><span class=\"u-color-open-access\">Open Access</span></span><time class=\"c-meta__item c-meta__item--block-at-lg\" datetime=\"2025-04-09\" itemprop=\"datePublished\">09 Apr 2025</time>\n        \n        \n    </div>","link":"https://www.nature.com/articles/s41586-025-08824-3","retrieved":1744220359357},{"title":"Immune checkpoint TIM-3 regulates microglia and Alzheimer’s disease (Nature - research articles)","contents":"<div class=\"c-card__layout u-full-height\">\n            \n                \n                    \n                        <div class=\"c-card__image\">\n                            <picture>\n                                <source type=\"image/webp\" srcset=\"\n                                    https://media.springernature.com/w165h90/springer-static/image/art%3A10.1038%2Fs41586-025-08852-z/MediaObjects/41586_2025_8852_Fig1_HTML.png?as=webp 160w,\n                                    https://media.springernature.com/w290h158/springer-static/image/art%3A10.1038%2Fs41586-025-08852-z/MediaObjects/41586_2025_8852_Fig1_HTML.png?as=webp 290w\" sizes=\"\n                                    (max-width: 640px) 160px,\n                                    (max-width: 1200px) 290px,\n                                    290px\">\n                                <img src=\"https://media.springernature.com/w290h158/springer-static/image/art%3A10.1038%2Fs41586-025-08852-z/MediaObjects/41586_2025_8852_Fig1_HTML.png\" alt=\"\" itemprop=\"image\">\n                            </picture>\n                        </div>\n                    \n                \n            \n            <div class=\"c-card__body u-display-flex u-flex-direction-column\">\n                <h3 class=\"c-card__title\" itemprop=\"name headline\">\n                    <a href=\"/articles/s41586-025-08852-z\" class=\"c-card__link u-link-inherit\" itemprop=\"url\" data-track=\"click\" data-track-action=\"view article\" data-track-label=\"link\">Immune checkpoint TIM-3 regulates microglia and Alzheimer’s disease</a>\n                </h3>\n                \n                    \n                        <div data-test=\"article-description\" class=\"c-card__summary u-mb-16 u-hide-sm-max\" itemprop=\"description\">\n                            <p>The immune-checkpoint molecule TIM-3 regulates microglial homeostasis, and its microglial-specific deletion reduced cognitive impairment in a mouse model of Alzheimer’s disease.</p>\n                        </div>\n                    \n                \n                \n                    \n<ul data-test=\"author-list\" class=\"c-author-list c-author-list--compact c-author-list--truncated\">\n    <li itemprop=\"creator\" itemscope=\"\" itemtype=\"http://schema.org/Person\"><span itemprop=\"name\">Kimitoshi Kimura</span></li><li itemprop=\"creator\" itemscope=\"\" itemtype=\"http://schema.org/Person\"><span itemprop=\"name\">Ayshwarya Subramanian</span></li><li itemprop=\"creator\" itemscope=\"\" itemtype=\"http://schema.org/Person\"><span itemprop=\"name\">Vijay K. Kuchroo</span></li>\n</ul>\n\n                \n                \n            </div>\n        </div>\n        \n            \n    <div class=\"c-card__section c-meta\">\n        <span class=\"c-meta__item c-meta__item--block-at-lg\" data-test=\"article.type\"><span class=\"c-meta__type\">Article</span></span><time class=\"c-meta__item c-meta__item--block-at-lg\" datetime=\"2025-04-09\" itemprop=\"datePublished\">09 Apr 2025</time>\n        \n        \n    </div>","link":"https://www.nature.com/articles/s41586-025-08852-z","retrieved":1744220359359},{"title":"Active energy compression of a laser-plasma electron beam (Nature - research articles)","contents":"<div class=\"c-card__layout u-full-height\">\n            \n                \n                    \n                        <div class=\"c-card__image\">\n                            <picture>\n                                <source type=\"image/webp\" srcset=\"\n                                    https://media.springernature.com/w165h90/springer-static/image/art%3A10.1038%2Fs41586-025-08772-y/MediaObjects/41586_2025_8772_Fig1_HTML.png?as=webp 160w,\n                                    https://media.springernature.com/w290h158/springer-static/image/art%3A10.1038%2Fs41586-025-08772-y/MediaObjects/41586_2025_8772_Fig1_HTML.png?as=webp 290w\" sizes=\"\n                                    (max-width: 640px) 160px,\n                                    (max-width: 1200px) 290px,\n                                    290px\">\n                                <img src=\"https://media.springernature.com/w290h158/springer-static/image/art%3A10.1038%2Fs41586-025-08772-y/MediaObjects/41586_2025_8772_Fig1_HTML.png\" alt=\"\" itemprop=\"image\">\n                            </picture>\n                        </div>\n                    \n                \n            \n            <div class=\"c-card__body u-display-flex u-flex-direction-column\">\n                <h3 class=\"c-card__title\" itemprop=\"name headline\">\n                    <a href=\"/articles/s41586-025-08772-y\" class=\"c-card__link u-link-inherit\" itemprop=\"url\" data-track=\"click\" data-track-action=\"view article\" data-track-label=\"link\">Active energy compression of a laser-plasma electron beam</a>\n                </h3>\n                \n                    \n                        <div data-test=\"article-description\" class=\"c-card__summary u-mb-16 u-hide-sm-max\" itemprop=\"description\">\n                            <p>A laser-plasma electron beam generated using active energy compression demonstrates reduction in energy spread and jitter by an order of magnitude to below the permille level, comparable with modern radio-frequency accelerators.</p>\n                        </div>\n                    \n                \n                \n                    \n<ul data-test=\"author-list\" class=\"c-author-list c-author-list--compact c-author-list--truncated\">\n    <li itemprop=\"creator\" itemscope=\"\" itemtype=\"http://schema.org/Person\"><span itemprop=\"name\">P. Winkler</span></li><li itemprop=\"creator\" itemscope=\"\" itemtype=\"http://schema.org/Person\"><span itemprop=\"name\">M. Trunk</span></li><li itemprop=\"creator\" itemscope=\"\" itemtype=\"http://schema.org/Person\"><span itemprop=\"name\">A. R. Maier</span></li>\n</ul>\n\n                \n                \n            </div>\n        </div>\n        \n            \n    <div class=\"c-card__section c-meta\">\n        <span class=\"c-meta__item c-meta__item--block-at-lg\" data-test=\"article.type\"><span class=\"c-meta__type\">Article</span></span><span class=\"c-meta__item c-meta__item--block-at-lg\" itemprop=\"openAccess\" data-test=\"open-access\"><span class=\"u-color-open-access\">Open Access</span></span><time class=\"c-meta__item c-meta__item--block-at-lg\" datetime=\"2025-04-09\" itemprop=\"datePublished\">09 Apr 2025</time>\n        \n        \n    </div>","link":"https://www.nature.com/articles/s41586-025-08772-y","retrieved":1744220359362},{"title":"Swinging lever mechanism of myosin directly shown by time-resolved cryo-EM (Nature - research articles)","contents":"<div class=\"c-card__layout u-full-height\">\n            \n                \n                    \n                        <div class=\"c-card__image\">\n                            <picture>\n                                <source type=\"image/webp\" srcset=\"\n                                    https://media.springernature.com/w165h90/springer-static/image/art%3A10.1038%2Fs41586-025-08876-5/MediaObjects/41586_2025_8876_Fig1_HTML.png?as=webp 160w,\n                                    https://media.springernature.com/w290h158/springer-static/image/art%3A10.1038%2Fs41586-025-08876-5/MediaObjects/41586_2025_8876_Fig1_HTML.png?as=webp 290w\" sizes=\"\n                                    (max-width: 640px) 160px,\n                                    (max-width: 1200px) 290px,\n                                    290px\">\n                                <img src=\"https://media.springernature.com/w290h158/springer-static/image/art%3A10.1038%2Fs41586-025-08876-5/MediaObjects/41586_2025_8876_Fig1_HTML.png\" alt=\"\" itemprop=\"image\">\n                            </picture>\n                        </div>\n                    \n                \n            \n            <div class=\"c-card__body u-display-flex u-flex-direction-column\">\n                <h3 class=\"c-card__title\" itemprop=\"name headline\">\n                    <a href=\"/articles/s41586-025-08876-5\" class=\"c-card__link u-link-inherit\" itemprop=\"url\" data-track=\"click\" data-track-action=\"view article\" data-track-label=\"link\">Swinging lever mechanism of myosin directly shown by time-resolved cryo-EM</a>\n                </h3>\n                \n                    \n                        <div data-test=\"article-description\" class=\"c-card__summary u-mb-16 u-hide-sm-max\" itemprop=\"description\">\n                            <p>A study using time-resolved cryogenic electron microscopy reveals the swinging lever mechanism of myosin, providing information on the molecular basis behind the production of force and movement by myosin.</p>\n                        </div>\n                    \n                \n                \n                    \n<ul data-test=\"author-list\" class=\"c-author-list c-author-list--compact c-author-list--truncated\">\n    <li itemprop=\"creator\" itemscope=\"\" itemtype=\"http://schema.org/Person\"><span itemprop=\"name\">David P. Klebl</span></li><li itemprop=\"creator\" itemscope=\"\" itemtype=\"http://schema.org/Person\"><span itemprop=\"name\">Sean N. McMillan</span></li><li itemprop=\"creator\" itemscope=\"\" itemtype=\"http://schema.org/Person\"><span itemprop=\"name\">Howard D. White</span></li>\n</ul>\n\n                \n                \n            </div>\n        </div>\n        \n            \n    <div class=\"c-card__section c-meta\">\n        <span class=\"c-meta__item c-meta__item--block-at-lg\" data-test=\"article.type\"><span class=\"c-meta__type\">Article</span></span><span class=\"c-meta__item c-meta__item--block-at-lg\" itemprop=\"openAccess\" data-test=\"open-access\"><span class=\"u-color-open-access\">Open Access</span></span><time class=\"c-meta__item c-meta__item--block-at-lg\" datetime=\"2025-04-09\" itemprop=\"datePublished\">09 Apr 2025</time>\n        \n        \n    </div>","link":"https://www.nature.com/articles/s41586-025-08876-5","retrieved":1744220359364},{"title":"Foundation model of neural activity predicts response to new stimulus types (Nature - research articles)","contents":"<div class=\"c-card__layout u-full-height\">\n            \n                \n                    \n                        <div class=\"c-card__image\">\n                            <picture>\n                                <source type=\"image/webp\" srcset=\"\n                                    https://media.springernature.com/w165h90/springer-static/image/art%3A10.1038%2Fs41586-025-08829-y/MediaObjects/41586_2025_8829_Fig1_HTML.png?as=webp 160w,\n                                    https://media.springernature.com/w290h158/springer-static/image/art%3A10.1038%2Fs41586-025-08829-y/MediaObjects/41586_2025_8829_Fig1_HTML.png?as=webp 290w\" sizes=\"\n                                    (max-width: 640px) 160px,\n                                    (max-width: 1200px) 290px,\n                                    290px\">\n                                <img src=\"https://media.springernature.com/w290h158/springer-static/image/art%3A10.1038%2Fs41586-025-08829-y/MediaObjects/41586_2025_8829_Fig1_HTML.png\" alt=\"\" itemprop=\"image\">\n                            </picture>\n                        </div>\n                    \n                \n            \n            <div class=\"c-card__body u-display-flex u-flex-direction-column\">\n                <h3 class=\"c-card__title\" itemprop=\"name headline\">\n                    <a href=\"/articles/s41586-025-08829-y\" class=\"c-card__link u-link-inherit\" itemprop=\"url\" data-track=\"click\" data-track-action=\"view article\" data-track-label=\"link\">Foundation model of neural activity predicts response to new stimulus types</a>\n                </h3>\n                \n                    \n                        <div data-test=\"article-description\" class=\"c-card__summary u-mb-16 u-hide-sm-max\" itemprop=\"description\">\n                            <p>A foundation model trained on neural activity of visual cortex from multiple mice accurately predicts responses to video stimuli and cell types, dendritic features and connectivity within the MICrONS functional connectomics dataset.</p>\n                        </div>\n                    \n                \n                \n                    \n<ul data-test=\"author-list\" class=\"c-author-list c-author-list--compact c-author-list--truncated\">\n    <li itemprop=\"creator\" itemscope=\"\" itemtype=\"http://schema.org/Person\"><span itemprop=\"name\">Eric Y. Wang</span></li><li itemprop=\"creator\" itemscope=\"\" itemtype=\"http://schema.org/Person\"><span itemprop=\"name\">Paul G. Fahey</span></li><li itemprop=\"creator\" itemscope=\"\" itemtype=\"http://schema.org/Person\"><span itemprop=\"name\">Andreas S. Tolias</span></li>\n</ul>\n\n                \n                \n            </div>\n        </div>\n        \n            \n    <div class=\"c-card__section c-meta\">\n        <span class=\"c-meta__item c-meta__item--block-at-lg\" data-test=\"article.type\"><span class=\"c-meta__type\">Article</span></span><span class=\"c-meta__item c-meta__item--block-at-lg\" itemprop=\"openAccess\" data-test=\"open-access\"><span class=\"u-color-open-access\">Open Access</span></span><time class=\"c-meta__item c-meta__item--block-at-lg\" datetime=\"2025-04-09\" itemprop=\"datePublished\">09 Apr 2025</time>\n        \n        \n    </div>","link":"https://www.nature.com/articles/s41586-025-08829-y","retrieved":1744220359366},{"title":"Leaf absorption contributes to accumulation of microplastics in plants (Nature - research articles)","contents":"<div class=\"c-card__layout u-full-height\">\n            \n                \n                    \n                        <div class=\"c-card__image\">\n                            <picture>\n                                <source type=\"image/webp\" srcset=\"\n                                    https://media.springernature.com/w165h90/springer-static/image/art%3A10.1038%2Fs41586-025-08831-4/MediaObjects/41586_2025_8831_Fig1_HTML.png?as=webp 160w,\n                                    https://media.springernature.com/w290h158/springer-static/image/art%3A10.1038%2Fs41586-025-08831-4/MediaObjects/41586_2025_8831_Fig1_HTML.png?as=webp 290w\" sizes=\"\n                                    (max-width: 640px) 160px,\n                                    (max-width: 1200px) 290px,\n                                    290px\">\n                                <img src=\"https://media.springernature.com/w290h158/springer-static/image/art%3A10.1038%2Fs41586-025-08831-4/MediaObjects/41586_2025_8831_Fig1_HTML.png\" alt=\"\" itemprop=\"image\">\n                            </picture>\n                        </div>\n                    \n                \n            \n            <div class=\"c-card__body u-display-flex u-flex-direction-column\">\n                <h3 class=\"c-card__title\" itemprop=\"name headline\">\n                    <a href=\"/articles/s41586-025-08831-4\" class=\"c-card__link u-link-inherit\" itemprop=\"url\" data-track=\"click\" data-track-action=\"view article\" data-track-label=\"link\">Leaf absorption contributes to accumulation of microplastics in plants</a>\n                </h3>\n                \n                    \n                        <div data-test=\"article-description\" class=\"c-card__summary u-mb-16 u-hide-sm-max\" itemprop=\"description\">\n                            <p>Absorption and accumulation of atmospheric microplastics by plant leaves occurs widely in the environment.</p>\n                        </div>\n                    \n                \n                \n                    \n<ul data-test=\"author-list\" class=\"c-author-list c-author-list--compact c-author-list--truncated\">\n    <li itemprop=\"creator\" itemscope=\"\" itemtype=\"http://schema.org/Person\"><span itemprop=\"name\">Ye Li</span></li><li itemprop=\"creator\" itemscope=\"\" itemtype=\"http://schema.org/Person\"><span itemprop=\"name\">Junjie Zhang</span></li><li itemprop=\"creator\" itemscope=\"\" itemtype=\"http://schema.org/Person\"><span itemprop=\"name\">Lei Wang</span></li>\n</ul>\n\n                \n                \n            </div>\n        </div>\n        \n            \n    <div class=\"c-card__section c-meta\">\n        <span class=\"c-meta__item c-meta__item--block-at-lg\" data-test=\"article.type\"><span class=\"c-meta__type\">Article</span></span><time class=\"c-meta__item c-meta__item--block-at-lg\" datetime=\"2025-04-09\" itemprop=\"datePublished\">09 Apr 2025</time>\n        \n        \n    </div>","link":"https://www.nature.com/articles/s41586-025-08831-4","retrieved":1744220359367},{"title":"Phenotypic complexities of rare heterozygous neurexin-1 deletions (Nature - research articles)","contents":"<div class=\"c-card__layout u-full-height\">\n            \n                \n                    \n                        <div class=\"c-card__image\">\n                            <picture>\n                                <source type=\"image/webp\" srcset=\"\n                                    https://media.springernature.com/w165h90/springer-static/image/art%3A10.1038%2Fs41586-025-08864-9/MediaObjects/41586_2025_8864_Fig1_HTML.png?as=webp 160w,\n                                    https://media.springernature.com/w290h158/springer-static/image/art%3A10.1038%2Fs41586-025-08864-9/MediaObjects/41586_2025_8864_Fig1_HTML.png?as=webp 290w\" sizes=\"\n                                    (max-width: 640px) 160px,\n                                    (max-width: 1200px) 290px,\n                                    290px\">\n                                <img src=\"https://media.springernature.com/w290h158/springer-static/image/art%3A10.1038%2Fs41586-025-08864-9/MediaObjects/41586_2025_8864_Fig1_HTML.png\" alt=\"\" itemprop=\"image\">\n                            </picture>\n                        </div>\n                    \n                \n            \n            <div class=\"c-card__body u-display-flex u-flex-direction-column\">\n                <h3 class=\"c-card__title\" itemprop=\"name headline\">\n                    <a href=\"/articles/s41586-025-08864-9\" class=\"c-card__link u-link-inherit\" itemprop=\"url\" data-track=\"click\" data-track-action=\"view article\" data-track-label=\"link\">Phenotypic complexities of rare heterozygous neurexin-1 deletions</a>\n                </h3>\n                \n                    \n                        <div data-test=\"article-description\" class=\"c-card__summary u-mb-16 u-hide-sm-max\" itemprop=\"description\">\n                            <p>How <i>NRXN1</i> variants affect multiple neuropsychiatric disorders is explored.</p>\n                        </div>\n                    \n                \n                \n                    \n<ul data-test=\"author-list\" class=\"c-author-list c-author-list--compact c-author-list--truncated\">\n    <li itemprop=\"creator\" itemscope=\"\" itemtype=\"http://schema.org/Person\"><span itemprop=\"name\">Michael B. Fernando</span></li><li itemprop=\"creator\" itemscope=\"\" itemtype=\"http://schema.org/Person\"><span itemprop=\"name\">Yu Fan</span></li><li itemprop=\"creator\" itemscope=\"\" itemtype=\"http://schema.org/Person\"><span itemprop=\"name\">Kristen J. Brennand</span></li>\n</ul>\n\n                \n                \n            </div>\n        </div>\n        \n            \n    <div class=\"c-card__section c-meta\">\n        <span class=\"c-meta__item c-meta__item--block-at-lg\" data-test=\"article.type\"><span class=\"c-meta__type\">Article</span></span><time class=\"c-meta__item c-meta__item--block-at-lg\" datetime=\"2025-04-09\" itemprop=\"datePublished\">09 Apr 2025</time>\n        \n        \n    </div>","link":"https://www.nature.com/articles/s41586-025-08864-9","retrieved":1744220359369},{"title":"Human assembloid model of the ascending neural sensory pathway (Nature - research articles)","contents":"<div class=\"c-card__layout u-full-height\">\n            \n                \n                    \n                        <div class=\"c-card__image\">\n                            <picture>\n                                <source type=\"image/webp\" srcset=\"\n                                    https://media.springernature.com/w165h90/springer-static/image/art%3A10.1038%2Fs41586-025-08808-3/MediaObjects/41586_2025_8808_Fig1_HTML.png?as=webp 160w,\n                                    https://media.springernature.com/w290h158/springer-static/image/art%3A10.1038%2Fs41586-025-08808-3/MediaObjects/41586_2025_8808_Fig1_HTML.png?as=webp 290w\" sizes=\"\n                                    (max-width: 640px) 160px,\n                                    (max-width: 1200px) 290px,\n                                    290px\">\n                                <img src=\"https://media.springernature.com/w290h158/springer-static/image/art%3A10.1038%2Fs41586-025-08808-3/MediaObjects/41586_2025_8808_Fig1_HTML.png\" alt=\"\" itemprop=\"image\">\n                            </picture>\n                        </div>\n                    \n                \n            \n            <div class=\"c-card__body u-display-flex u-flex-direction-column\">\n                <h3 class=\"c-card__title\" itemprop=\"name headline\">\n                    <a href=\"/articles/s41586-025-08808-3\" class=\"c-card__link u-link-inherit\" itemprop=\"url\" data-track=\"click\" data-track-action=\"view article\" data-track-label=\"link\">Human assembloid model of the ascending neural sensory pathway</a>\n                </h3>\n                \n                    \n                        <div data-test=\"article-description\" class=\"c-card__summary u-mb-16 u-hide-sm-max\" itemprop=\"description\">\n                            <p>A human ascending somatosensory assembloid model was developed, which integrates multiple organoids to simulate the spinothalamic pathway, demonstrating functional connectivity and responsiveness to stimuli and revealing insights into pain-related genetic mutations.</p>\n                        </div>\n                    \n                \n                \n                    \n<ul data-test=\"author-list\" class=\"c-author-list c-author-list--compact c-author-list--truncated\">\n    <li itemprop=\"creator\" itemscope=\"\" itemtype=\"http://schema.org/Person\"><span itemprop=\"name\">Ji-il Kim</span></li><li itemprop=\"creator\" itemscope=\"\" itemtype=\"http://schema.org/Person\"><span itemprop=\"name\">Kent Imaizumi</span></li><li itemprop=\"creator\" itemscope=\"\" itemtype=\"http://schema.org/Person\"><span itemprop=\"name\">Sergiu P. Pașca</span></li>\n</ul>\n\n                \n                \n            </div>\n        </div>\n        \n            \n    <div class=\"c-card__section c-meta\">\n        <span class=\"c-meta__item c-meta__item--block-at-lg\" data-test=\"article.type\"><span class=\"c-meta__type\">Article</span></span><span class=\"c-meta__item c-meta__item--block-at-lg\" itemprop=\"openAccess\" data-test=\"open-access\"><span class=\"u-color-open-access\">Open Access</span></span><time class=\"c-meta__item c-meta__item--block-at-lg\" datetime=\"2025-04-09\" itemprop=\"datePublished\">09 Apr 2025</time>\n        \n        \n    </div>","link":"https://www.nature.com/articles/s41586-025-08808-3","retrieved":1744220359371},{"title":"Perisomatic ultrastructure efficiently classifies cells in mouse cortex (Nature - research articles)","contents":"<div class=\"c-card__layout u-full-height\">\n            \n                \n                    \n                        <div class=\"c-card__image\">\n                            <picture>\n                                <source type=\"image/webp\" srcset=\"\n                                    https://media.springernature.com/w165h90/springer-static/image/art%3A10.1038%2Fs41586-024-07765-7/MediaObjects/41586_2024_7765_Fig1_HTML.png?as=webp 160w,\n                                    https://media.springernature.com/w290h158/springer-static/image/art%3A10.1038%2Fs41586-024-07765-7/MediaObjects/41586_2024_7765_Fig1_HTML.png?as=webp 290w\" sizes=\"\n                                    (max-width: 640px) 160px,\n                                    (max-width: 1200px) 290px,\n                                    290px\">\n                                <img src=\"https://media.springernature.com/w290h158/springer-static/image/art%3A10.1038%2Fs41586-024-07765-7/MediaObjects/41586_2024_7765_Fig1_HTML.png\" alt=\"\" itemprop=\"image\">\n                            </picture>\n                        </div>\n                    \n                \n            \n            <div class=\"c-card__body u-display-flex u-flex-direction-column\">\n                <h3 class=\"c-card__title\" itemprop=\"name headline\">\n                    <a href=\"/articles/s41586-024-07765-7\" class=\"c-card__link u-link-inherit\" itemprop=\"url\" data-track=\"click\" data-track-action=\"view article\" data-track-label=\"link\">Perisomatic ultrastructure efficiently classifies cells in mouse cortex</a>\n                </h3>\n                \n                    \n                        <div data-test=\"article-description\" class=\"c-card__summary u-mb-16 u-hide-sm-max\" itemprop=\"description\">\n                            <p>An analysis demonstrates that quantitative measurements of perisomatic ultrastructure features of neurons can be used to categorize them into cell types.</p>\n                        </div>\n                    \n                \n                \n                    \n<ul data-test=\"author-list\" class=\"c-author-list c-author-list--compact c-author-list--truncated\">\n    <li itemprop=\"creator\" itemscope=\"\" itemtype=\"http://schema.org/Person\"><span itemprop=\"name\">Leila Elabbady</span></li><li itemprop=\"creator\" itemscope=\"\" itemtype=\"http://schema.org/Person\"><span itemprop=\"name\">Sharmishtaa Seshamani</span></li><li itemprop=\"creator\" itemscope=\"\" itemtype=\"http://schema.org/Person\"><span itemprop=\"name\">Forrest Collman</span></li>\n</ul>\n\n                \n                \n            </div>\n        </div>\n        \n            \n    <div class=\"c-card__section c-meta\">\n        <span class=\"c-meta__item c-meta__item--block-at-lg\" data-test=\"article.type\"><span class=\"c-meta__type\">Article</span></span><span class=\"c-meta__item c-meta__item--block-at-lg\" itemprop=\"openAccess\" data-test=\"open-access\"><span class=\"u-color-open-access\">Open Access</span></span><time class=\"c-meta__item c-meta__item--block-at-lg\" datetime=\"2025-04-09\" itemprop=\"datePublished\">09 Apr 2025</time>\n        \n        \n    </div>","link":"https://www.nature.com/articles/s41586-024-07765-7","retrieved":1744220359373},{"title":"Comprehensive interrogation of synthetic lethality in the DNA damage response (Nature - research articles)","contents":"<div class=\"c-card__layout u-full-height\">\n            \n                \n                    \n                        <div class=\"c-card__image\">\n                            <picture>\n                                <source type=\"image/webp\" srcset=\"\n                                    https://media.springernature.com/w165h90/springer-static/image/art%3A10.1038%2Fs41586-025-08815-4/MediaObjects/41586_2025_8815_Fig1_HTML.png?as=webp 160w,\n                                    https://media.springernature.com/w290h158/springer-static/image/art%3A10.1038%2Fs41586-025-08815-4/MediaObjects/41586_2025_8815_Fig1_HTML.png?as=webp 290w\" sizes=\"\n                                    (max-width: 640px) 160px,\n                                    (max-width: 1200px) 290px,\n                                    290px\">\n                                <img src=\"https://media.springernature.com/w290h158/springer-static/image/art%3A10.1038%2Fs41586-025-08815-4/MediaObjects/41586_2025_8815_Fig1_HTML.png\" alt=\"\" itemprop=\"image\">\n                            </picture>\n                        </div>\n                    \n                \n            \n            <div class=\"c-card__body u-display-flex u-flex-direction-column\">\n                <h3 class=\"c-card__title\" itemprop=\"name headline\">\n                    <a href=\"/articles/s41586-025-08815-4\" class=\"c-card__link u-link-inherit\" itemprop=\"url\" data-track=\"click\" data-track-action=\"view article\" data-track-label=\"link\">Comprehensive interrogation of synthetic lethality in the DNA damage response</a>\n                </h3>\n                \n                    \n                        <div data-test=\"article-description\" class=\"c-card__summary u-mb-16 u-hide-sm-max\" itemprop=\"description\">\n                            <p>Combinatorial CRISPRi screening was used to map genetic interactions in DNA damage response pathways, revealing known and new connections, including the roles of WDR48 and USP1 in preventing under-replication and SMARCAL1 and FANCM in remodelling persistent cruciform DNA structures.</p>\n                        </div>\n                    \n                \n                \n                    \n<ul data-test=\"author-list\" class=\"c-author-list c-author-list--compact c-author-list--truncated\">\n    <li itemprop=\"creator\" itemscope=\"\" itemtype=\"http://schema.org/Person\"><span itemprop=\"name\">John Fielden</span></li><li itemprop=\"creator\" itemscope=\"\" itemtype=\"http://schema.org/Person\"><span itemprop=\"name\">Sebastian M. Siegner</span></li><li itemprop=\"creator\" itemscope=\"\" itemtype=\"http://schema.org/Person\"><span itemprop=\"name\">Jacob E. Corn</span></li>\n</ul>\n\n                \n                \n            </div>\n        </div>\n        \n            \n    <div class=\"c-card__section c-meta\">\n        <span class=\"c-meta__item c-meta__item--block-at-lg\" data-test=\"article.type\"><span class=\"c-meta__type\">Article</span></span><span class=\"c-meta__item c-meta__item--block-at-lg\" itemprop=\"openAccess\" data-test=\"open-access\"><span class=\"u-color-open-access\">Open Access</span></span><time class=\"c-meta__item c-meta__item--block-at-lg\" datetime=\"2025-04-09\" itemprop=\"datePublished\">09 Apr 2025</time>\n        \n        \n    </div>","link":"https://www.nature.com/articles/s41586-025-08815-4","retrieved":1744220359374},{"title":"Seismic imaging of a basaltic Lesser Antilles slab from ancient tectonics (Nature - research articles)","contents":"<div class=\"c-card__layout u-full-height\">\n            \n                \n                    \n                        <div class=\"c-card__image\">\n                            <picture>\n                                <source type=\"image/webp\" srcset=\"\n                                    https://media.springernature.com/w165h90/springer-static/image/art%3A10.1038%2Fs41586-025-08754-0/MediaObjects/41586_2025_8754_Fig1_HTML.png?as=webp 160w,\n                                    https://media.springernature.com/w290h158/springer-static/image/art%3A10.1038%2Fs41586-025-08754-0/MediaObjects/41586_2025_8754_Fig1_HTML.png?as=webp 290w\" sizes=\"\n                                    (max-width: 640px) 160px,\n                                    (max-width: 1200px) 290px,\n                                    290px\">\n                                <img src=\"https://media.springernature.com/w290h158/springer-static/image/art%3A10.1038%2Fs41586-025-08754-0/MediaObjects/41586_2025_8754_Fig1_HTML.png\" alt=\"\" itemprop=\"image\">\n                            </picture>\n                        </div>\n                    \n                \n            \n            <div class=\"c-card__body u-display-flex u-flex-direction-column\">\n                <h3 class=\"c-card__title\" itemprop=\"name headline\">\n                    <a href=\"/articles/s41586-025-08754-0\" class=\"c-card__link u-link-inherit\" itemprop=\"url\" data-track=\"click\" data-track-action=\"view article\" data-track-label=\"link\">Seismic imaging of a basaltic Lesser Antilles slab from ancient tectonics</a>\n                </h3>\n                \n                    \n                        <div data-test=\"article-description\" class=\"c-card__summary u-mb-16 u-hide-sm-max\" itemprop=\"description\">\n                            <p>Imaging of the mantle transition zone beneath the Lesser Antilles shows a basalt-rich region within the subducting slab near the proposed location of a subducted extinct spreading ridge, implying ancient tectonics play a role in influencing slab trajectories.</p>\n                        </div>\n                    \n                \n                \n                    \n<ul data-test=\"author-list\" class=\"c-author-list c-author-list--compact c-author-list--truncated\">\n    <li itemprop=\"creator\" itemscope=\"\" itemtype=\"http://schema.org/Person\"><span itemprop=\"name\">Xusong Yang</span></li><li itemprop=\"creator\" itemscope=\"\" itemtype=\"http://schema.org/Person\"><span itemprop=\"name\">Yujiang Xie</span></li><li itemprop=\"creator\" itemscope=\"\" itemtype=\"http://schema.org/Person\"><span itemprop=\"name\">Richard Robertson</span></li>\n</ul>\n\n                \n                \n            </div>\n        </div>\n        \n            \n    <div class=\"c-card__section c-meta\">\n        <span class=\"c-meta__item c-meta__item--block-at-lg\" data-test=\"article.type\"><span class=\"c-meta__type\">Article</span></span><span class=\"c-meta__item c-meta__item--block-at-lg\" itemprop=\"openAccess\" data-test=\"open-access\"><span class=\"u-color-open-access\">Open Access</span></span><time class=\"c-meta__item c-meta__item--block-at-lg\" datetime=\"2025-04-09\" itemprop=\"datePublished\">09 Apr 2025</time>\n        \n        \n    </div>","link":"https://www.nature.com/articles/s41586-025-08754-0","retrieved":1744220359375},{"title":"Giant electrocaloric effect in high-polar-entropy perovskite oxides (Nature - research articles)","contents":"<div class=\"c-card__layout u-full-height\">\n            \n                \n                    \n                        <div class=\"c-card__image\">\n                            <picture>\n                                <source type=\"image/webp\" srcset=\"\n                                    https://media.springernature.com/w165h90/springer-static/image/art%3A10.1038%2Fs41586-025-08768-8/MediaObjects/41586_2025_8768_Fig1_HTML.png?as=webp 160w,\n                                    https://media.springernature.com/w290h158/springer-static/image/art%3A10.1038%2Fs41586-025-08768-8/MediaObjects/41586_2025_8768_Fig1_HTML.png?as=webp 290w\" sizes=\"\n                                    (max-width: 640px) 160px,\n                                    (max-width: 1200px) 290px,\n                                    290px\">\n                                <img src=\"https://media.springernature.com/w290h158/springer-static/image/art%3A10.1038%2Fs41586-025-08768-8/MediaObjects/41586_2025_8768_Fig1_HTML.png\" alt=\"\" itemprop=\"image\">\n                            </picture>\n                        </div>\n                    \n                \n            \n            <div class=\"c-card__body u-display-flex u-flex-direction-column\">\n                <h3 class=\"c-card__title\" itemprop=\"name headline\">\n                    <a href=\"/articles/s41586-025-08768-8\" class=\"c-card__link u-link-inherit\" itemprop=\"url\" data-track=\"click\" data-track-action=\"view article\" data-track-label=\"link\">Giant electrocaloric effect in high-polar-entropy perovskite oxides</a>\n                </h3>\n                \n                    \n                        <div data-test=\"article-description\" class=\"c-card__summary u-mb-16 u-hide-sm-max\" itemprop=\"description\">\n                            <p>Targeted multielement substitution of a lead-free relaxor ferroelectric perovskite distorts the lattice structure and induces strong polar disorder, leading to high-polar-entropy ferroelectric oxides with a high electrocaloric effect and long lifetime.</p>\n                        </div>\n                    \n                \n                \n                    \n<ul data-test=\"author-list\" class=\"c-author-list c-author-list--compact c-author-list--truncated\">\n    <li itemprop=\"creator\" itemscope=\"\" itemtype=\"http://schema.org/Person\"><span itemprop=\"name\">Feihong Du</span></li><li itemprop=\"creator\" itemscope=\"\" itemtype=\"http://schema.org/Person\"><span itemprop=\"name\">Tiannan Yang</span></li><li itemprop=\"creator\" itemscope=\"\" itemtype=\"http://schema.org/Person\"><span itemprop=\"name\">Xiaoshi Qian</span></li>\n</ul>\n\n                \n                \n            </div>\n        </div>\n        \n            \n    <div class=\"c-card__section c-meta\">\n        <span class=\"c-meta__item c-meta__item--block-at-lg\" data-test=\"article.type\"><span class=\"c-meta__type\">Article</span></span><time class=\"c-meta__item c-meta__item--block-at-lg\" datetime=\"2025-04-09\" itemprop=\"datePublished\">09 Apr 2025</time>\n        \n        \n    </div>","link":"https://www.nature.com/articles/s41586-025-08768-8","retrieved":1744220359377},{"title":"A non-contact wearable device for monitoring epidermal molecular flux (Nature - research articles)","contents":"<div class=\"c-card__layout u-full-height\">\n            \n                \n                    \n                        <div class=\"c-card__image\">\n                            <picture>\n                                <source type=\"image/webp\" srcset=\"\n                                    https://media.springernature.com/w165h90/springer-static/image/art%3A10.1038%2Fs41586-025-08825-2/MediaObjects/41586_2025_8825_Fig1_HTML.png?as=webp 160w,\n                                    https://media.springernature.com/w290h158/springer-static/image/art%3A10.1038%2Fs41586-025-08825-2/MediaObjects/41586_2025_8825_Fig1_HTML.png?as=webp 290w\" sizes=\"\n                                    (max-width: 640px) 160px,\n                                    (max-width: 1200px) 290px,\n                                    290px\">\n                                <img src=\"https://media.springernature.com/w290h158/springer-static/image/art%3A10.1038%2Fs41586-025-08825-2/MediaObjects/41586_2025_8825_Fig1_HTML.png\" alt=\"\" itemprop=\"image\">\n                            </picture>\n                        </div>\n                    \n                \n            \n            <div class=\"c-card__body u-display-flex u-flex-direction-column\">\n                <h3 class=\"c-card__title\" itemprop=\"name headline\">\n                    <a href=\"/articles/s41586-025-08825-2\" class=\"c-card__link u-link-inherit\" itemprop=\"url\" data-track=\"click\" data-track-action=\"view article\" data-track-label=\"link\">A non-contact wearable device for monitoring epidermal molecular flux</a>\n                </h3>\n                \n                    \n                        <div data-test=\"article-description\" class=\"c-card__summary u-mb-16 u-hide-sm-max\" itemprop=\"description\">\n                            <p>A non-contact wearable device that defines and modulates a microclimate adjacent to the skin can measure incoming and outgoing streams of vapourized substances, offering valuable insights into physiological health, wound healing and environmental exposures.</p>\n                        </div>\n                    \n                \n                \n                    \n<ul data-test=\"author-list\" class=\"c-author-list c-author-list--compact c-author-list--truncated\">\n    <li itemprop=\"creator\" itemscope=\"\" itemtype=\"http://schema.org/Person\"><span itemprop=\"name\">Jaeho Shin</span></li><li itemprop=\"creator\" itemscope=\"\" itemtype=\"http://schema.org/Person\"><span itemprop=\"name\">Joseph Woojin Song</span></li><li itemprop=\"creator\" itemscope=\"\" itemtype=\"http://schema.org/Person\"><span itemprop=\"name\">John A. Rogers</span></li>\n</ul>\n\n                \n                \n            </div>\n        </div>\n        \n            \n    <div class=\"c-card__section c-meta\">\n        <span class=\"c-meta__item c-meta__item--block-at-lg\" data-test=\"article.type\"><span class=\"c-meta__type\">Article</span></span><time class=\"c-meta__item c-meta__item--block-at-lg\" datetime=\"2025-04-09\" itemprop=\"datePublished\">09 Apr 2025</time>\n        \n        \n    </div>","link":"https://www.nature.com/articles/s41586-025-08825-2","retrieved":1744220359379},{"title":"Reprogramming site-specific retrotransposon activity to new DNA sites (Nature - research articles)","contents":"<div class=\"c-card__layout u-full-height\">\n            \n                \n                    \n                        <div class=\"c-card__image\">\n                            <picture>\n                                <source type=\"image/webp\" srcset=\"\n                                    https://media.springernature.com/w165h90/springer-static/image/art%3A10.1038%2Fs41586-025-08877-4/MediaObjects/41586_2025_8877_Fig1_HTML.png?as=webp 160w,\n                                    https://media.springernature.com/w290h158/springer-static/image/art%3A10.1038%2Fs41586-025-08877-4/MediaObjects/41586_2025_8877_Fig1_HTML.png?as=webp 290w\" sizes=\"\n                                    (max-width: 640px) 160px,\n                                    (max-width: 1200px) 290px,\n                                    290px\">\n                                <img src=\"https://media.springernature.com/w290h158/springer-static/image/art%3A10.1038%2Fs41586-025-08877-4/MediaObjects/41586_2025_8877_Fig1_HTML.png\" alt=\"\" itemprop=\"image\">\n                            </picture>\n                        </div>\n                    \n                \n            \n            <div class=\"c-card__body u-display-flex u-flex-direction-column\">\n                <h3 class=\"c-card__title\" itemprop=\"name headline\">\n                    <a href=\"/articles/s41586-025-08877-4\" class=\"c-card__link u-link-inherit\" itemprop=\"url\" data-track=\"click\" data-track-action=\"view article\" data-track-label=\"link\">Reprogramming site-specific retrotransposon activity to new DNA sites</a>\n                </h3>\n                \n                    \n                        <div data-test=\"article-description\" class=\"c-card__summary u-mb-16 u-hide-sm-max\" itemprop=\"description\">\n                            <p>A study of retrotransposon activity repurposes a retroelement called R2<i>Tocc</i> to create a programmable system called STITCHR that enables diverse&nbsp;genome edits including efficient, scarless large payload&nbsp;insertions.</p>\n                        </div>\n                    \n                \n                \n                    \n<ul data-test=\"author-list\" class=\"c-author-list c-author-list--compact c-author-list--truncated\">\n    <li itemprop=\"creator\" itemscope=\"\" itemtype=\"http://schema.org/Person\"><span itemprop=\"name\">Christopher W. Fell</span></li><li itemprop=\"creator\" itemscope=\"\" itemtype=\"http://schema.org/Person\"><span itemprop=\"name\">Lukas Villiger</span></li><li itemprop=\"creator\" itemscope=\"\" itemtype=\"http://schema.org/Person\"><span itemprop=\"name\">Jonathan S. Gootenberg</span></li>\n</ul>\n\n                \n                \n            </div>\n        </div>\n        \n            \n    <div class=\"c-card__section c-meta\">\n        <span class=\"c-meta__item c-meta__item--block-at-lg\" data-test=\"article.type\"><span class=\"c-meta__type\">Article</span></span><time class=\"c-meta__item c-meta__item--block-at-lg\" datetime=\"2025-04-09\" itemprop=\"datePublished\">09 Apr 2025</time>\n        \n        \n    </div>","link":"https://www.nature.com/articles/s41586-025-08877-4","retrieved":1744220359381},{"title":"Hunter-gatherer sea voyages extended to remotest Mediterranean islands (Nature - research articles)","contents":"<div class=\"c-card__layout u-full-height\">\n            \n                \n                    \n                        <div class=\"c-card__image\">\n                            <picture>\n                                <source type=\"image/webp\" srcset=\"\n                                    https://media.springernature.com/w165h90/springer-static/image/art%3A10.1038%2Fs41586-025-08780-y/MediaObjects/41586_2025_8780_Fig1_HTML.png?as=webp 160w,\n                                    https://media.springernature.com/w290h158/springer-static/image/art%3A10.1038%2Fs41586-025-08780-y/MediaObjects/41586_2025_8780_Fig1_HTML.png?as=webp 290w\" sizes=\"\n                                    (max-width: 640px) 160px,\n                                    (max-width: 1200px) 290px,\n                                    290px\">\n                                <img src=\"https://media.springernature.com/w290h158/springer-static/image/art%3A10.1038%2Fs41586-025-08780-y/MediaObjects/41586_2025_8780_Fig1_HTML.png\" alt=\"\" itemprop=\"image\">\n                            </picture>\n                        </div>\n                    \n                \n            \n            <div class=\"c-card__body u-display-flex u-flex-direction-column\">\n                <h3 class=\"c-card__title\" itemprop=\"name headline\">\n                    <a href=\"/articles/s41586-025-08780-y\" class=\"c-card__link u-link-inherit\" itemprop=\"url\" data-track=\"click\" data-track-action=\"view article\" data-track-label=\"link\">Hunter-gatherer sea voyages extended to remotest Mediterranean islands</a>\n                </h3>\n                \n                    \n                        <div data-test=\"article-description\" class=\"c-card__summary u-mb-16 u-hide-sm-max\" itemprop=\"description\">\n                            <p>Archaeological discoveries from Malta suggest that humans were present on the Maltese islands from around 8,500 years ago, providing evidence that Mesolithic hunter-gatherers made sea crossings as long as 100 km.</p>\n                        </div>\n                    \n                \n                \n                    \n<ul data-test=\"author-list\" class=\"c-author-list c-author-list--compact c-author-list--truncated\">\n    <li itemprop=\"creator\" itemscope=\"\" itemtype=\"http://schema.org/Person\"><span itemprop=\"name\">Eleanor M. L. Scerri</span></li><li itemprop=\"creator\" itemscope=\"\" itemtype=\"http://schema.org/Person\"><span itemprop=\"name\">James Blinkhorn</span></li><li itemprop=\"creator\" itemscope=\"\" itemtype=\"http://schema.org/Person\"><span itemprop=\"name\">Nicholas C. Vella</span></li>\n</ul>\n\n                \n                \n            </div>\n        </div>\n        \n            \n    <div class=\"c-card__section c-meta\">\n        <span class=\"c-meta__item c-meta__item--block-at-lg\" data-test=\"article.type\"><span class=\"c-meta__type\">Article</span></span><span class=\"c-meta__item c-meta__item--block-at-lg\" itemprop=\"openAccess\" data-test=\"open-access\"><span class=\"u-color-open-access\">Open Access</span></span><time class=\"c-meta__item c-meta__item--block-at-lg\" datetime=\"2025-04-09\" itemprop=\"datePublished\">09 Apr 2025</time>\n        \n        \n    </div>","link":"https://www.nature.com/articles/s41586-025-08780-y","retrieved":1744220359382},{"title":"NEURD offers automated proofreading and feature extraction for connectomics (Nature - research articles)","contents":"<div class=\"c-card__layout u-full-height\">\n            \n                \n                    \n                        <div class=\"c-card__image\">\n                            <picture>\n                                <source type=\"image/webp\" srcset=\"\n                                    https://media.springernature.com/w165h90/springer-static/image/art%3A10.1038%2Fs41586-025-08660-5/MediaObjects/41586_2025_8660_Fig1_HTML.png?as=webp 160w,\n                                    https://media.springernature.com/w290h158/springer-static/image/art%3A10.1038%2Fs41586-025-08660-5/MediaObjects/41586_2025_8660_Fig1_HTML.png?as=webp 290w\" sizes=\"\n                                    (max-width: 640px) 160px,\n                                    (max-width: 1200px) 290px,\n                                    290px\">\n                                <img src=\"https://media.springernature.com/w290h158/springer-static/image/art%3A10.1038%2Fs41586-025-08660-5/MediaObjects/41586_2025_8660_Fig1_HTML.png\" alt=\"\" itemprop=\"image\">\n                            </picture>\n                        </div>\n                    \n                \n            \n            <div class=\"c-card__body u-display-flex u-flex-direction-column\">\n                <h3 class=\"c-card__title\" itemprop=\"name headline\">\n                    <a href=\"/articles/s41586-025-08660-5\" class=\"c-card__link u-link-inherit\" itemprop=\"url\" data-track=\"click\" data-track-action=\"view article\" data-track-label=\"link\">NEURD offers automated proofreading and feature extraction for connectomics</a>\n                </h3>\n                \n                    \n                        <div data-test=\"article-description\" class=\"c-card__summary u-mb-16 u-hide-sm-max\" itemprop=\"description\">\n                            <p>Neural Decomposition (NEURD) is a software package that decomposes neuronal data from high-resolution electron microscopy volumes into feature-rich graph representations to facilitate analysis for neuroscience research.</p>\n                        </div>\n                    \n                \n                \n                    \n<ul data-test=\"author-list\" class=\"c-author-list c-author-list--compact c-author-list--truncated\">\n    <li itemprop=\"creator\" itemscope=\"\" itemtype=\"http://schema.org/Person\"><span itemprop=\"name\">Brendan Celii</span></li><li itemprop=\"creator\" itemscope=\"\" itemtype=\"http://schema.org/Person\"><span itemprop=\"name\">Stelios Papadopoulos</span></li><li itemprop=\"creator\" itemscope=\"\" itemtype=\"http://schema.org/Person\"><span itemprop=\"name\">Jacob Reimer</span></li>\n</ul>\n\n                \n                \n            </div>\n        </div>\n        \n            \n    <div class=\"c-card__section c-meta\">\n        <span class=\"c-meta__item c-meta__item--block-at-lg\" data-test=\"article.type\"><span class=\"c-meta__type\">Article</span></span><span class=\"c-meta__item c-meta__item--block-at-lg\" itemprop=\"openAccess\" data-test=\"open-access\"><span class=\"u-color-open-access\">Open Access</span></span><time class=\"c-meta__item c-meta__item--block-at-lg\" datetime=\"2025-04-09\" itemprop=\"datePublished\">09 Apr 2025</time>\n        \n        \n    </div>","link":"https://www.nature.com/articles/s41586-025-08660-5","retrieved":1744220359383},{"title":"Complete sequencing of ape genomes (Nature - research articles)","contents":"<div class=\"c-card__layout u-full-height\">\n            \n                \n                    \n                        <div class=\"c-card__image\">\n                            <picture>\n                                <source type=\"image/webp\" srcset=\"\n                                    https://media.springernature.com/w165h90/springer-static/image/art%3A10.1038%2Fs41586-025-08816-3/MediaObjects/41586_2025_8816_Fig1_HTML.png?as=webp 160w,\n                                    https://media.springernature.com/w290h158/springer-static/image/art%3A10.1038%2Fs41586-025-08816-3/MediaObjects/41586_2025_8816_Fig1_HTML.png?as=webp 290w\" sizes=\"\n                                    (max-width: 640px) 160px,\n                                    (max-width: 1200px) 290px,\n                                    290px\">\n                                <img src=\"https://media.springernature.com/w290h158/springer-static/image/art%3A10.1038%2Fs41586-025-08816-3/MediaObjects/41586_2025_8816_Fig1_HTML.png\" alt=\"\" itemprop=\"image\">\n                            </picture>\n                        </div>\n                    \n                \n            \n            <div class=\"c-card__body u-display-flex u-flex-direction-column\">\n                <h3 class=\"c-card__title\" itemprop=\"name headline\">\n                    <a href=\"/articles/s41586-025-08816-3\" class=\"c-card__link u-link-inherit\" itemprop=\"url\" data-track=\"click\" data-track-action=\"view article\" data-track-label=\"link\">Complete sequencing of ape genomes</a>\n                </h3>\n                \n                    \n                        <div data-test=\"article-description\" class=\"c-card__summary u-mb-16 u-hide-sm-max\" itemprop=\"description\">\n                            <p>Complete sequences of chromosomes telomere-to-telomere from chimpanzee, bonobo, gorilla, Bornean orangutan, Sumatran orangutan and siamang provide a comprehensive and valuable resource for future evolutionary comparisons.</p>\n                        </div>\n                    \n                \n                \n                    \n<ul data-test=\"author-list\" class=\"c-author-list c-author-list--compact c-author-list--truncated\">\n    <li itemprop=\"creator\" itemscope=\"\" itemtype=\"http://schema.org/Person\"><span itemprop=\"name\">DongAhn Yoo</span></li><li itemprop=\"creator\" itemscope=\"\" itemtype=\"http://schema.org/Person\"><span itemprop=\"name\">Arang Rhie</span></li><li itemprop=\"creator\" itemscope=\"\" itemtype=\"http://schema.org/Person\"><span itemprop=\"name\">Evan E. Eichler</span></li>\n</ul>\n\n                \n                \n            </div>\n        </div>\n        \n            \n    <div class=\"c-card__section c-meta\">\n        <span class=\"c-meta__item c-meta__item--block-at-lg\" data-test=\"article.type\"><span class=\"c-meta__type\">Article</span></span><span class=\"c-meta__item c-meta__item--block-at-lg\" itemprop=\"openAccess\" data-test=\"open-access\"><span class=\"u-color-open-access\">Open Access</span></span><time class=\"c-meta__item c-meta__item--block-at-lg\" datetime=\"2025-04-09\" itemprop=\"datePublished\">09 Apr 2025</time>\n        \n        \n    </div>","link":"https://www.nature.com/articles/s41586-025-08816-3","retrieved":1744220359385},{"title":"DNA-guided transcription factor interactions extend human gene regulatory code (Nature - research articles)","contents":"<div class=\"c-card__layout u-full-height\">\n            \n                \n                    \n                        <div class=\"c-card__image\">\n                            <picture>\n                                <source type=\"image/webp\" srcset=\"\n                                    https://media.springernature.com/w165h90/springer-static/image/art%3A10.1038%2Fs41586-025-08844-z/MediaObjects/41586_2025_8844_Fig1_HTML.png?as=webp 160w,\n                                    https://media.springernature.com/w290h158/springer-static/image/art%3A10.1038%2Fs41586-025-08844-z/MediaObjects/41586_2025_8844_Fig1_HTML.png?as=webp 290w\" sizes=\"\n                                    (max-width: 640px) 160px,\n                                    (max-width: 1200px) 290px,\n                                    290px\">\n                                <img src=\"https://media.springernature.com/w290h158/springer-static/image/art%3A10.1038%2Fs41586-025-08844-z/MediaObjects/41586_2025_8844_Fig1_HTML.png\" alt=\"\" itemprop=\"image\">\n                            </picture>\n                        </div>\n                    \n                \n            \n            <div class=\"c-card__body u-display-flex u-flex-direction-column\">\n                <h3 class=\"c-card__title\" itemprop=\"name headline\">\n                    <a href=\"/articles/s41586-025-08844-z\" class=\"c-card__link u-link-inherit\" itemprop=\"url\" data-track=\"click\" data-track-action=\"view article\" data-track-label=\"link\">DNA-guided transcription factor interactions extend human gene regulatory code</a>\n                </h3>\n                \n                    \n                        <div data-test=\"article-description\" class=\"c-card__summary u-mb-16 u-hide-sm-max\" itemprop=\"description\">\n                            <p>A large-scale analysis of DNA-bound transcription factors (TFs) shows how the presence of DNA markedly affects the landscape of TF interactions, and identifies composite motifs that are recognized by complexes of TFs rather than by individual ones.</p>\n                        </div>\n                    \n                \n                \n                    \n<ul data-test=\"author-list\" class=\"c-author-list c-author-list--compact c-author-list--truncated\">\n    <li itemprop=\"creator\" itemscope=\"\" itemtype=\"http://schema.org/Person\"><span itemprop=\"name\">Zhiyuan Xie</span></li><li itemprop=\"creator\" itemscope=\"\" itemtype=\"http://schema.org/Person\"><span itemprop=\"name\">Ilya Sokolov</span></li><li itemprop=\"creator\" itemscope=\"\" itemtype=\"http://schema.org/Person\"><span itemprop=\"name\">Jussi Taipale</span></li>\n</ul>\n\n                \n                \n            </div>\n        </div>\n        \n            \n    <div class=\"c-card__section c-meta\">\n        <span class=\"c-meta__item c-meta__item--block-at-lg\" data-test=\"article.type\"><span class=\"c-meta__type\">Article</span></span><span class=\"c-meta__item c-meta__item--block-at-lg\" itemprop=\"openAccess\" data-test=\"open-access\"><span class=\"u-color-open-access\">Open Access</span></span><time class=\"c-meta__item c-meta__item--block-at-lg\" datetime=\"2025-04-09\" itemprop=\"datePublished\">09 Apr 2025</time>\n        \n        \n    </div>","link":"https://www.nature.com/articles/s41586-025-08844-z","retrieved":1744220359386},{"title":"Plotting Fluorescent Spectra (Brady Johnston)","contents":"<h5 class=\"no-anchor card-title listing-title\">\nPlotting Fluorescent Spectra\n</h5>\n<div class=\"listing-categories\">\n<div class=\"listing-category\" onclick=\"window.quartoListingCategory('Z2dwbG90Mg=='); return false;\">\nggplot2\n</div>\n<div class=\"listing-category\" onclick=\"window.quartoListingCategory('Ug=='); return false;\">\nR\n</div>\n<div class=\"listing-category\" onclick=\"window.quartoListingCategory('Y29kaW5n'); return false;\">\ncoding\n</div>\n<div class=\"listing-category\" onclick=\"window.quartoListingCategory('Zmx1b3Jlc2VuY2U='); return false;\">\nfluoresence\n</div>\n</div>\n<div class=\"card-text listing-description\">\nHow do we go about plotting some spectral data from fluorophores, to get something like below?\n</div>\n<div class=\"card-attribution card-text-small justify\">\n<div class=\"listing-author\">\nBrady Johnston\n</div>\n<div class=\"listing-date\">\nSep 3, 2022\n</div>\n</div>","retrieved":1744479501873},{"title":"Interactively Visualising Proteins (Brady Johnston)","contents":"<h5 class=\"no-anchor card-title listing-title\">\nInteractively Visualising Proteins\n</h5>\n<div class=\"listing-categories\">\n<div class=\"listing-category\" onclick=\"window.quartoListingCategory('YmlvaW5mb3JtYXRpY3M='); return false;\">\nbioinformatics\n</div>\n<div class=\"listing-category\" onclick=\"window.quartoListingCategory('Ug=='); return false;\">\nR\n</div>\n<div class=\"listing-category\" onclick=\"window.quartoListingCategory('cHJvdGVpbg=='); return false;\">\nprotein\n</div>\n</div>\n<div class=\"card-text listing-description\">\nRecently I’ve been doing a lot of structural bioinformatics. To avoid having to export my results into PyMol of Chimerax, I wanted a better solution that could embed the…\n</div>\n<div class=\"card-attribution card-text-small justify\">\n<div class=\"listing-author\">\nBrady Johnston\n</div>\n<div class=\"listing-date\">\nFeb 15, 2021\n</div>\n</div>","retrieved":1744479501876},{"title":"Visualising Global Rubbish (Brady Johnston)","contents":"<h5 class=\"no-anchor card-title listing-title\">\nVisualising Global Rubbish\n</h5>\n<div class=\"listing-categories\">\n<div class=\"listing-category\" onclick=\"window.quartoListingCategory('Ug=='); return false;\">\nR\n</div>\n<div class=\"listing-category\" onclick=\"window.quartoListingCategory('dGlkeXR1ZXNkYXk='); return false;\">\ntidytuesday\n</div>\n<div class=\"listing-category\" onclick=\"window.quartoListingCategory('ZGF0YSB2aXM='); return false;\">\ndata vis\n</div>\n</div>\n<div class=\"card-text listing-description\">\nFor this week’s #tidytuesday, I visualise the vast dataset of rubbish collected on the beaches all over the world.\n</div>\n<div class=\"card-attribution card-text-small justify\">\n<div class=\"listing-author\">\nBrady Johnston\n</div>\n<div class=\"listing-date\">\nJan 31, 2021\n</div>\n</div>","retrieved":1744479501878},{"title":"R for Biologists (Brady Johnston)","contents":"<h5 class=\"no-anchor card-title listing-title\">\nR for Biologists\n</h5>\n<div class=\"listing-categories\">\n<div class=\"listing-category\" onclick=\"window.quartoListingCategory('Ug=='); return false;\">\nR\n</div>\n<div class=\"listing-category\" onclick=\"window.quartoListingCategory('dHV0b3JpYWw='); return false;\">\ntutorial\n</div>\n</div>\n<div class=\"card-text listing-description\">\nA couple of months ago I ran (with lots of help for content) an R for biologists workshop.\n</div>\n<div class=\"card-attribution card-text-small justify\">\n<div class=\"listing-author\">\nBrady Johnston\n</div>\n<div class=\"listing-date\">\nJul 7, 2020\n</div>\n</div>","retrieved":1744479501879},{"title":"Praise for pdb-tools (Brady Johnston)","contents":"<h5 class=\"no-anchor card-title listing-title\">\nPraise for <code>pdb-tools</code>\n</h5>\n<div class=\"listing-categories\">\n<div class=\"listing-category\" onclick=\"window.quartoListingCategory('cHl0aG9u'); return false;\">\npython\n</div>\n<div class=\"listing-category\" onclick=\"window.quartoListingCategory('c3RydWN0dXJhbCBiaW9sb2d5'); return false;\">\nstructural biology\n</div>\n<div class=\"listing-category\" onclick=\"window.quartoListingCategory('YmFzaA=='); return false;\">\nbash\n</div>\n</div>\n<div class=\"card-text listing-description\">\nAn output from some MD work left me with a <code>.pdb</code> file with <code>0.00</code> <em>b-factors</em>.\n</div>\n<div class=\"card-attribution card-text-small justify\">\n<div class=\"listing-author\">\nBrady Johnston\n</div>\n<div class=\"listing-date\">\nJun 9, 2020\n</div>\n</div>","retrieved":1744479501881},{"title":"Blender for Biochemists. (Brady Johnston)","contents":"<h5 class=\"no-anchor card-title listing-title\">\nBlender for Biochemists.\n</h5>\n<div class=\"listing-categories\">\n<div class=\"listing-category\" onclick=\"window.quartoListingCategory('YmxlbmRlcg=='); return false;\">\nblender\n</div>\n<div class=\"listing-category\" onclick=\"window.quartoListingCategory('c2NpYXJ0'); return false;\">\nsciart\n</div>\n<div class=\"listing-category\" onclick=\"window.quartoListingCategory('eW91dHViZQ=='); return false;\">\nyoutube\n</div>\n<div class=\"listing-category\" onclick=\"window.quartoListingCategory('dHV0b3JpYWw='); return false;\">\ntutorial\n</div>\n</div>\n<div class=\"card-text listing-description\">\nI’ve started my journey into the realm of youtube.\n</div>\n<div class=\"card-attribution card-text-small justify\">\n<div class=\"listing-author\">\nBrady Johnston\n</div>\n<div class=\"listing-date\">\nMay 6, 2020\n</div>\n</div>","retrieved":1744479501883},{"title":"Rendering around crashes with Animation Nodes (Brady Johnston)","contents":"<h5 class=\"no-anchor card-title listing-title\">\nRendering around crashes with Animation Nodes\n</h5>\n<div class=\"listing-categories\">\n<div class=\"listing-category\" onclick=\"window.quartoListingCategory('YmxlbmRlcg=='); return false;\">\nblender\n</div>\n<div class=\"listing-category\" onclick=\"window.quartoListingCategory('c3RydWN0dXJhbCBiaW9sb2d5'); return false;\">\nstructural biology\n</div>\n<div class=\"listing-category\" onclick=\"window.quartoListingCategory('bm9kZXM='); return false;\">\nnodes\n</div>\n</div>\n<div class=\"card-text listing-description\">\nCan we make some pixelated protein art?\n</div>\n<div class=\"card-attribution card-text-small justify\">\n<div class=\"listing-author\">\nBrady Johnston\n</div>\n<div class=\"listing-date\">\nApr 5, 2020\n</div>\n</div>","retrieved":1744479501884},{"title":"GFP as a Hat (Brady Johnston)","contents":"<h5 class=\"no-anchor card-title listing-title\">\nGFP as a Hat\n</h5>\n<div class=\"listing-categories\">\n<div class=\"listing-category\" onclick=\"window.quartoListingCategory('YmxlbmRlcg=='); return false;\">\nblender\n</div>\n<div class=\"listing-category\" onclick=\"window.quartoListingCategory('cHJvdGVpbg=='); return false;\">\nprotein\n</div>\n<div class=\"listing-category\" onclick=\"window.quartoListingCategory('QVI='); return false;\">\nAR\n</div>\n</div>\n<div class=\"card-text listing-description\">\nAs I was drifting off to sleep one night, the thought hit me:\n</div>\n<div class=\"card-attribution card-text-small justify\">\n<div class=\"listing-author\">\nBrady Johnston\n</div>\n<div class=\"listing-date\">\nAug 16, 2019\n</div>\n</div>","retrieved":1744479501887}]}